{
    "access-broker": "weiyu@datawiza.com",
    "datawiza-access-broker": "weiyu@datawiza.com",
    "airflow": "\"2022-10-26T11",
    "amd-gpu": "\"2023-08-29T12",
    "argo-cd": "\"2022-10-26T02",
    "artifactory-ha": "rimasm@jfrog.com",
    "artifactory-jcr": "vinaya@jfrog.com",
    "asserts": "\"2022-10-20T20",
    "cassandra": "\"2022-10-26T11",
    "cert-manager": "cert-manager-maintainers@googlegroups.com",
    "cf-runtime": "\"2023-03-28T14",
    "cf-runner": "\"2021-12-20T11",
    "chronicle": "\"2023-07-19T14",
    "citrix-adc-istio-ingress-gateway": "subash.dangol@citrix.com",
    "citrix-cpx-istio-sidecar-injector": "ajeeta.shakeet@citrix.com",
    "citrix-cpx-with-ingress-controller": "subash.dangol@citrix.com",
    "citrix-ingress-controller": "subash.dangol@citrix.com",
    "cloudcasa": "info@catalogicsoftware.com",
    "cockroachdb": "helm-charts@cockroachlabs.com",
    "community-operator": "support@mongodb.com",
    "confluent-for-kubernetes": "operator@confluent.io",
    "consul": "\"2022-10-18T04",
    "streamsets": "thomas.ganka@streamsets.com",
    "cost-analyzer": "\"2022-12-15T10",
    "kubecost": "\"2021-06-23T17",
    "crate-operator": "\"2022-10-26T02",
    "isilon": "\"2023-05-04T18",
    "csi-powermax": "\"2023-04-18T16",
    "powerstore": "\"2023-03-28T15",
    "csi-powerstore": "\"2023-03-28T15",
    "unity": "\"2023-03-30T09",
    "csi-unity": "\"2022-12-01T02",
    "vxflexos": "\"2022-05-13T12",
    "csi-wekafsplugin": "\"2021-06-23T17",
    "datadog": "support@datadoghq.com",
    "datadog-operator": "support@datadoghq.com",
    "dxemssql": "support@dh2i.com",
    "dynatrace-operator": "lukas.hinterreiter@dynatrace.com",
    "elasticsearch": "helm-charts@elastic.co",
    "external-secrets": "kellinmcavoy@gmail.com",
    "external-secrets-operator": "kellinmcavoy@gmail.com",
    "f5-bigip-ctlr": "f5_cis_operators@f5.com",
    "falcon-sensor": "integrations@crowdstrike.com",
    "falcon-helm": "gabriel.alford@crowdstrike.com",
    "federatorai": "support@prophetstor.com",
    "fpga-operator": "info@inaccel.com",
    "inaccel": "info@inaccel.com",
    "gluu": "support@gluu.org",
    "gopaddle": "\"2023-01-27T16",
    "haproxy": "dkorunic@haproxy.com",
    "harbor": "yshengwen@vmware.com",
    "hpe-array-exporter": "hpe-containers-dev@hpe.com",
    "hpe-csi-driver": "hpe-containers-dev@hpe.com",
    "hpe-csi-info-metrics": "hpe-containers-dev@hpe.com",
    "instana-agent": "nathan.fisher@instana.com",
    "intel-device-plugins-operator": "\"2022-10-26T02",
    "intel-device-plugins-qat": "\"2023-03-03T14",
    "intel-device-plugins-sgx": "\"2023-03-03T14",
    "jaeger-operator": "batazor111@gmail.com",
    "jenkins": "timjacomb1@gmail.com",
    "k8s-triliovault-operator": "prafull.ladha@trilio.io",
    "k10": "support@kasten.io",
    "kafka": "\"2022-10-26T11",
    "kamaji": "iam@mendrugory.com",
    "kamaji-console": "me@bsctl.io",
    "kibana": "helm-charts@elastic.co",
    "kong": "traines@konghq.com",
    "koor-operator": "\"2023-07-31T23",
    "kubemq-cluster": "info@kubemq.io",
    "kubemq-controller": "info@kubemq.io",
    "kubemq-crds": "info@kubemq.io",
    "kubernetes-ingress-controller": "\"2023-10-04T15",
    "kubeslice-controller": "\"2022-12-02T16",
    "kubeslice-worker": "\"2022-12-02T16",
    "kuma": "nikolay.nikolaev@konghq.com",
    "kongmesh": "nikolay.nikolaev@konghq.com",
    "linkerd-control-plane": "cncf-linkerd-dev@lists.cncf.io",
    "loft": "info@loft.sh",
    "logstash": "helm-charts@elastic.co",
    "mariadb": "\"2022-10-26T11",
    "metallb": "\"2022-10-26T02",
    "minio-operator": "dev@minio.io",
    "operator": "dev@minio.io",
    "mysql": "\"2022-10-26T11",
    "nats": "jaime@nats.io",
    "nginx-ingress": "kubernetes@nginx.com",
    "nginx-ingress-controller": "kubernetes@nginx.com",
    "nginx-service-mesh": "\"2021-10-11T10",
    "nri-bundle": "\"2022-12-01T19",
    "newrelic-bundle": "cloudnative@nutanix.com",
    "nutanix-csi-snapshot": "cloudnative@nutanix.com",
    "nutanix-csi-storage": "\"2021-06-23T17",
    "ondat-operator": "angelos.perivolaropoulos@ondat.io",
    "openebs": "prateek.pandey@openebs.io",
    "pixie": "\"2022-05-03T10",
    "polaris": "robertb@fairwinds.com",
    "portshift-operator": "idan@portshift.io",
    "portworx": "dahuang@purestorage.com",
    "portworx-essentials": "dahuang@purestorage.com",
    "postgresql": "\"2022-10-26T11",
    "psmdb-db": "tomislav.plavcic@percona.com",
    "psmdb-operator": "tomislav.plavcic@percona.com",
    "pxc-db": "natalia.marukovich@percona.com",
    "pxc-operator": "sergey.pronin@percona.com",
    "quobyte-cluster": "\"2022-10-20T22",
    "redis": "\"2022-10-26T11",
    "redpanda": "\"2022-10-11T16",
    "s3gw": "s3gw@suse.com",
    "sextant": "\"2023-02-10T20",
    "shipa": "rlachhman@shipa.io",
    "spark": "\"2022-10-26T11",
    "speedscale-operator": "support@speedscale.com",
    "stackstate-k8s-agent": "ops@stackstate.com",
    "sumologic": "\"2022-10-18T02",
    "sysdig": "carlos.arilla@sysdig.com",
    "tcs-issuer": "\"2022-06-29T10",
    "tomcat": "\"2022-10-26T11",
    "traefik": "ldez@traefik.io",
    "triggermesh": "matt@triggermesh.com",
    "vals-operator": "info@digitalis.io",
    "vault": "\"2022-10-18T04",
    "wordpress": "\"2022-10-26T11",
    "yugabyte": "arnav@yugabyte.com",
    "yugaware": "arnav@yugabyte.com",
    "ziti-host": "\"2022-03-12T22",
    "zookeeper": "\"2022-10-26T11"
}